sqlalchemy_data_manager/__init__.py
sqlalchemy_data_manager/managers.py
sqlalchemy_data_manager-0.0.1.dist-info/LICENSE
sqlalchemy_data_manager-0.0.1.dist-info/METADATA
sqlalchemy_data_manager-0.0.1.dist-info/WHEEL
sqlalchemy_data_manager-0.0.1.dist-info/RECORD
