Metadata-Version: 2.3
Name: sqlalchemy-data-manager
Version: 0.0.1
Summary: Import sqlalchemy models from json/csv or export db data to json/csv.
License: Apache-2.0
Author: Sergey V. Elfimov
Author-email: elfimovserg@gmail.com
Requires-Python: >=3.11,<4.0
Classifier: License :: OSI Approved :: Apache Software License
Classifier: Natural Language :: English
Classifier: Operating System :: OS Independent
Classifier: Programming Language :: Python
Classifier: Programming Language :: Python :: 3
Classifier: Programming Language :: Python :: 3.11
Classifier: Programming Language :: Python :: 3.12
Classifier: Programming Language :: Python :: 3.13
Classifier: Programming Language :: Python :: 3 :: Only
Requires-Dist: SQLAlchemy (>=1.4.36,<2.1.0)
Project-URL: Repository, https://github.com/SergeiVElfimov/sqlalchemy-data-manager
